[
	{
		"inputs": [
			{
				"internalType": "uint256",
				"name": "_addStartDate",
				"type": "uint256"
			},
			{
				"internalType": "uint256",
				"name": "_addEndDate",
				"type": "uint256"
			},
			{
				"internalType": "uint256",
				"name": "_startDate",
				"type": "uint256"
			},
			{
				"internalType": "uint256",
				"name": "_endDate",
				"type": "uint256"
			},
			{
				"internalType": "uint256",
				"name": "_maxNominatedNum",
				"type": "uint256"
			},
			{
				"internalType": "uint256",
				"name": "_totalShareHold",
				"type": "uint256"
			},
			{
				"internalType": "uint256",
				"name": "_maxSharehold",
				"type": "uint256"
			},
			{
				"internalType": "uint256",
				"name": "_voteType",
				"type": "uint256"
			}
		],
		"payable": false,
		"stateMutability": "nonpayable",
		"type": "constructor"
	},
	{
		"anonymous": false,
		"inputs": [
			{
				"indexed": false,
				"internalType": "uint256",
				"name": "candidateId",
				"type": "uint256"
			},
			{
				"indexed": false,
				"internalType": "string",
				"name": "candidateName",
				"type": "string"
			},
			{
				"indexed": false,
				"internalType": "string",
				"name": "candidatePhoto",
				"type": "string"
			},
			{
				"indexed": false,
				"internalType": "string",
				"name": "candidateInfo",
				"type": "string"
			},
			{
				"indexed": false,
				"internalType": "uint256",
				"name": "candidateTotalVote",
				"type": "uint256"
			}
		],
		"name": "addCandidate",
		"type": "event"
	},
	{
		"anonymous": false,
		"inputs": [
			{
				"indexed": false,
				"internalType": "address",
				"name": "voter",
				"type": "address"
			},
			{
				"indexed": false,
				"internalType": "uint256",
				"name": "sharehold",
				"type": "uint256"
			}
		],
		"name": "deploySharehold",
		"type": "event"
	},
	{
		"anonymous": false,
		"inputs": [
			{
				"indexed": false,
				"internalType": "uint256",
				"name": "candidateId",
				"type": "uint256"
			},
			{
				"indexed": false,
				"internalType": "uint256",
				"name": "inputId",
				"type": "uint256"
			}
		],
		"name": "lookForInfo",
		"type": "event"
	},
	{
		"anonymous": false,
		"inputs": [
			{
				"indexed": false,
				"internalType": "address",
				"name": "myAddr",
				"type": "address"
			},
			{
				"indexed": false,
				"internalType": "uint256",
				"name": "recordID",
				"type": "uint256"
			},
			{
				"indexed": false,
				"internalType": "uint256",
				"name": "candidateID",
				"type": "uint256"
			},
			{
				"indexed": false,
				"internalType": "uint256",
				"name": "voteNum",
				"type": "uint256"
			}
		],
		"name": "lookUpMyVote",
		"type": "event"
	},
	{
		"anonymous": false,
		"inputs": [
			{
				"indexed": false,
				"internalType": "uint256",
				"name": "candidateId",
				"type": "uint256"
			},
			{
				"indexed": false,
				"internalType": "uint256",
				"name": "voteNum",
				"type": "uint256"
			}
		],
		"name": "newVoteRecord",
		"type": "event"
	},
	{
		"anonymous": false,
		"inputs": [
			{
				"indexed": false,
				"internalType": "uint256",
				"name": "voteName",
				"type": "uint256"
			},
			{
				"indexed": false,
				"internalType": "uint256",
				"name": "voteTime",
				"type": "uint256"
			},
			{
				"indexed": false,
				"internalType": "bool",
				"name": "hasVoted",
				"type": "bool"
			}
		],
		"name": "vote",
		"type": "event"
	},
	{
		"constant": true,
		"inputs": [],
		"name": "addCandidateEndDate",
		"outputs": [
			{
				"internalType": "uint256",
				"name": "",
				"type": "uint256"
			}
		],
		"payable": false,
		"stateMutability": "view",
		"type": "function"
	},
	{
		"constant": true,
		"inputs": [],
		"name": "addCandidateStartDate",
		"outputs": [
			{
				"internalType": "uint256",
				"name": "",
				"type": "uint256"
			}
		],
		"payable": false,
		"stateMutability": "view",
		"type": "function"
	},
	{
		"constant": true,
		"inputs": [
			{
				"internalType": "uint256",
				"name": "",
				"type": "uint256"
			}
		],
		"name": "candidates",
		"outputs": [
			{
				"internalType": "uint256",
				"name": "candidateId",
				"type": "uint256"
			},
			{
				"internalType": "string",
				"name": "candidateName",
				"type": "string"
			},
			{
				"internalType": "string",
				"name": "candidatePhoto",
				"type": "string"
			},
			{
				"internalType": "string",
				"name": "candidateInfo",
				"type": "string"
			},
			{
				"internalType": "uint256",
				"name": "candidateTotalVote",
				"type": "uint256"
			}
		],
		"payable": false,
		"stateMutability": "view",
		"type": "function"
	},
	{
		"constant": false,
		"inputs": [
			{
				"internalType": "uint256",
				"name": "_candidateId",
				"type": "uint256"
			},
			{
				"internalType": "uint256",
				"name": "_newVote",
				"type": "uint256"
			},
			{
				"internalType": "uint256",
				"name": "_voteInfoNum",
				"type": "uint256"
			},
			{
				"internalType": "uint256",
				"name": "_currentDate",
				"type": "uint256"
			}
		],
		"name": "changeMyVote",
		"outputs": [],
		"payable": false,
		"stateMutability": "nonpayable",
		"type": "function"
	},
	{
		"constant": false,
		"inputs": [
			{
				"internalType": "string",
				"name": "_cadidateName",
				"type": "string"
			},
			{
				"internalType": "string",
				"name": "_candidatePhoto",
				"type": "string"
			},
			{
				"internalType": "string",
				"name": "_cadidateInfo",
				"type": "string"
			},
			{
				"internalType": "uint256",
				"name": "_currentDate",
				"type": "uint256"
			}
		],
		"name": "createNewCandidate",
		"outputs": [],
		"payable": false,
		"stateMutability": "nonpayable",
		"type": "function"
	},
	{
		"constant": true,
		"inputs": [],
		"name": "currentTotalShareHold",
		"outputs": [
			{
				"internalType": "uint256",
				"name": "",
				"type": "uint256"
			}
		],
		"payable": false,
		"stateMutability": "view",
		"type": "function"
	},
	{
		"constant": false,
		"inputs": [
			{
				"internalType": "address",
				"name": "_voterAddr",
				"type": "address"
			},
			{
				"internalType": "uint256",
				"name": "_shareHold",
				"type": "uint256"
			}
		],
		"name": "deployShareHold",
		"outputs": [],
		"payable": false,
		"stateMutability": "nonpayable",
		"type": "function"
	},
	{
		"constant": false,
		"inputs": [
			{
				"internalType": "uint256",
				"name": "_recordId",
				"type": "uint256"
			}
		],
		"name": "lookUpVoteRecord",
		"outputs": [],
		"payable": false,
		"stateMutability": "nonpayable",
		"type": "function"
	},
	{
		"constant": true,
		"inputs": [],
		"name": "totalCandidateNumber",
		"outputs": [
			{
				"internalType": "uint256",
				"name": "",
				"type": "uint256"
			}
		],
		"payable": false,
		"stateMutability": "view",
		"type": "function"
	},
	{
		"constant": true,
		"inputs": [],
		"name": "voteDeployer",
		"outputs": [
			{
				"internalType": "address",
				"name": "",
				"type": "address"
			}
		],
		"payable": false,
		"stateMutability": "view",
		"type": "function"
	},
	{
		"constant": true,
		"inputs": [],
		"name": "voteEndDate",
		"outputs": [
			{
				"internalType": "uint256",
				"name": "",
				"type": "uint256"
			}
		],
		"payable": false,
		"stateMutability": "view",
		"type": "function"
	},
	{
		"constant": false,
		"inputs": [
			{
				"internalType": "uint256",
				"name": "_candidateId",
				"type": "uint256"
			},
			{
				"internalType": "uint256",
				"name": "_voteNum",
				"type": "uint256"
			},
			{
				"internalType": "uint256",
				"name": "_currentDate",
				"type": "uint256"
			}
		],
		"name": "voteForCandidate",
		"outputs": [],
		"payable": false,
		"stateMutability": "nonpayable",
		"type": "function"
	},
	{
		"constant": true,
		"inputs": [],
		"name": "voteName",
		"outputs": [
			{
				"internalType": "string",
				"name": "",
				"type": "string"
			}
		],
		"payable": false,
		"stateMutability": "view",
		"type": "function"
	},
	{
		"constant": true,
		"inputs": [],
		"name": "voteStartDate",
		"outputs": [
			{
				"internalType": "uint256",
				"name": "",
				"type": "uint256"
			}
		],
		"payable": false,
		"stateMutability": "view",
		"type": "function"
	},
	{
		"constant": true,
		"inputs": [
			{
				"internalType": "address",
				"name": "",
				"type": "address"
			}
		],
		"name": "voters",
		"outputs": [
			{
				"internalType": "uint256",
				"name": "voteTime",
				"type": "uint256"
			},
			{
				"internalType": "uint256",
				"name": "sharehold",
				"type": "uint256"
			},
			{
				"internalType": "uint256",
				"name": "totalVoteNum",
				"type": "uint256"
			},
			{
				"internalType": "uint256",
				"name": "voteUsed",
				"type": "uint256"
			},
			{
				"internalType": "uint256",
				"name": "numOfPeopleNominated",
				"type": "uint256"
			},
			{
				"internalType": "bool",
				"name": "hasVoted",
				"type": "bool"
			}
		],
		"payable": false,
		"stateMutability": "view",
		"type": "function"
	}
]